django_fac/__init__.py
django_fac/apps.py
django_fac/tests.py
django_fac/views.py
django_fac/core/__init__.py
django_fac/core/constants.py
django_fac/core/entities.py
django_fac/core/payment.py
django_fac/core/utils.py
django_fac-0.1.dev1.dist-info/LICENSE
django_fac-0.1.dev1.dist-info/METADATA
django_fac-0.1.dev1.dist-info/WHEEL
django_fac-0.1.dev1.dist-info/top_level.txt
django_fac-0.1.dev1.dist-info/RECORD
