Metadata-Version: 2.1
Name: django-fac
Version: 0.1.dev1
Summary: django-fac is a Django app to conduct that is used to integrate with First Atlantic Commerce payment gateway
Home-page: https://github.com/realdecoy/django-fac/
Author: Davane Davis
Author-email: ddavis@realdecoy.com
License: MIT
Classifier: Environment :: Web Environment
Classifier: Development Status :: 1 - Planning
Classifier: Framework :: Django
Classifier: Framework :: Django :: 2.2
Classifier: Intended Audience :: Developers
Classifier: License :: OSI Approved :: MIT License
Classifier: Operating System :: OS Independent
Classifier: Programming Language :: Python :: 3 :: Only
Classifier: Programming Language :: Python :: 3.7
Classifier: Programming Language :: Python :: Implementation :: CPython
Classifier: Topic :: Software Development :: Libraries :: Application Frameworks
Classifier: Topic :: Software Development :: Libraries :: Python Modules
Requires-Python: >=3.7
License-File: LICENSE
Requires-Dist: Django (>=2.2.2)
Requires-Dist: requests (>=2.22.0)
